mixbalanced/README.MD
mixbalanced/__init__.py
mixbalanced/requirements.txt
mixbalanced/thirdparty.json
mixbalanced-0.10.dist-info/LICENSE.rst
mixbalanced-0.10.dist-info/METADATA
mixbalanced-0.10.dist-info/WHEEL
mixbalanced-0.10.dist-info/top_level.txt
mixbalanced-0.10.dist-info/RECORD
