Metadata-Version: 2.1
Name: mixbalanced
Version: 0.10
Summary: Mixes the elements of multiple lists in a balanced manner based on their proportional lengths.
Home-page: https://github.com/hansalemaos/mixbalanced
Author: Johannes Fischer
Author-email: aulasparticularesdealemaosp@gmail.com
License: MIT
Keywords: mix,elements,balanced
Classifier: Development Status :: 4 - Beta
Classifier: Programming Language :: Python :: 3 :: Only
Classifier: Programming Language :: Python :: 3.10
Classifier: Topic :: Software Development :: Libraries :: Python Modules
Classifier: Topic :: Utilities
License-File: LICENSE.rst
